[{"name":"Lana Kurayeva Hair Academy","website":" lanakurayeva.com ","phone":" +1 929-444-8601 ","address":" 397 3rd Ave Suite 101, New York, NY 10016, United States ","has_website":true,"has_phone":true,"total_reviews":"More","ratings":"5","url":"https://www.google.com/maps/search/Salon+in+New+York"},{"name":".Cartel Hair Studio, SOHO Barber Shop","website":" cartelstudio.co ","phone":" +1 934-212-0600 ","address":" 87 Crosby St, New York, NY 10012, United States ","has_website":true,"has_phone":true,"total_reviews":"More","ratings":"4.5","url":"https://www.google.com/maps/place/Lana+Kurayeva+Hair+Academy/@40.7421548,-74.0525963,13z/data=!3m1!5s0x89c25909a95b1a7f:0x3952a94c4f2275b0!4m9!1m2!2m1!1sSalon+in+New+York!3m5!1s0x89c25958be4204a7:0xa9b950be30542f02!8m2!3d40.7421548!4d-73.9804985!16s%2Fg%2F11vjxfpdz7?entry=ttu"},{"name":"Bon Bon Hair Salon & Spa","website":" bon-bon.com ","phone":" +1 212-286-5300 ","address":" 353 Lexington Ave, New York, NY 10016, United States ","has_website":true,"has_phone":true,"total_reviews":"More","ratings":"4.3","url":"https://www.google.com/maps/place/.Cartel+Hair+Studio,+SOHO+Barber+Shop/@40.7421548,-74.0525963,13z/data=!4m9!1m2!2m1!1sSalon+in+New+York!3m5!1s0x89c25908ab7bd1bd:0x692d82fe44d6a286!8m2!3d40.7232271!4d-73.9974088!16s%2Fg%2F11s18l3z25?entry=ttu"},{"name":"Shear Bliss NYC Salon","website":" shearblissnyc.com ","phone":" +1 212-213-6050 ","address":" 397 3rd Ave, New York, NY 10016, United States ","has_website":true,"has_phone":true,"total_reviews":"More","ratings":"4.8","url":"https://www.google.com/maps/place/Bon+Bon+Hair+Salon+%26+Spa/@40.7421548,-74.0525963,13z/data=!3m1!5s0x89c25903fd27abe9:0x5f995f8b3093a28a!4m10!1m2!2m1!1sSalon+in+New+York!3m6!1s0x89c2590422aa991f:0x34060c6c2e6eebc4!8m2!3d40.7498373!4d-73.976924!15sChFTYWxvbiBpbiBOZXcgWW9ya5IBCmhhaXJfc2Fsb27gAQA!16s%2Fg%2F1tfscr_9?entry=ttu"},{"name":"Timothy John's Salon NYC","website":" timothyjohnsalon.com ","phone":" +1 212-459-0130 ","address":" 888 8th Ave, New York, NY 10019, United States ","has_website":true,"has_phone":true,"total_reviews":"More","ratings":"5.0","url":"https://www.google.com/maps/place/Shear+Bliss+NYC+Salon/@40.7421548,-74.0525963,13z/data=!3m1!5s0x89c25909a95b1a7f:0x3952a94c4f2275b0!4m10!1m2!2m1!1sSalon+in+New+York!3m6!1s0x89c25909ae09ef2f:0x65edc579a408b5b7!8m2!3d40.7421615!4d-73.9805489!15sChFTYWxvbiBpbiBOZXcgWW9ya5IBCmhhaXJfc2Fsb27gAQA!16s%2Fg%2F1vgqd_nv?entry=ttu"},{"name":"T-Gardens New York Hair Salon","website":" t-gardens.com ","phone":" +1 212-350-9970 ","address":" 328 E 59th St, New York, NY 10022, United States ","has_website":true,"has_phone":true,"total_reviews":"More","ratings":"4.6","url":"https://www.google.com/maps/place/Timothy+John's+Salon+NYC/@40.7421548,-74.0525963,13z/data=!4m10!1m2!2m1!1sSalon+in+New+York!3m6!1s0x89c258579b050af7:0x75eb3a60b838812f!8m2!3d40.7637412!4d-73.9848822!15sChFTYWxvbiBpbiBOZXcgWW9ya5IBCmhhaXJfc2Fsb27gAQA!16s%2Fg%2F1td5h0pr?entry=ttu"},{"name":"Palms Salon","website":" palms-salon.com ","phone":" +1 646-599-3342 ","address":" 353 E 15th St FL 2, New York, NY 10003, United States ","has_website":true,"has_phone":true,"total_reviews":"More","ratings":"4.9","url":"https://www.google.com/maps/place/T-Gardens+New+York+Hair+Salon/@40.7421548,-74.0525963,13z/data=!4m10!1m2!2m1!1sSalon+in+New+York!3m6!1s0x89c258e6575b77a9:0x7cc70c18d03b6e0e!8m2!3d40.7598807!4d-73.9631684!15sChFTYWxvbiBpbiBOZXcgWW9ya1oTIhFzYWxvbiBpbiBuZXcgeW9ya5IBCmhhaXJfc2Fsb27gAQA!16s%2Fg%2F1261z599z?entry=ttu"}]